.bumpversion.cfg
.coveragerc
.travis.yml
AUTHORS.rst
CHANGELOG.rst
CONTRIBUTING.rst
LICENSE
MANIFEST.in
README.rst
appveyor.yml
bootstrap.py
setup.cfg
setup.py
tox.ini
conf/.travis.yml
conf/appveyor.yml
conf/tox.ini
docs/authors.rst
docs/changelog.rst
docs/conf.py
docs/contributing.rst
docs/index.rst
docs/installation.rst
docs/readme.rst
docs/requirements.txt
docs/sample.png
docs/spelling_wordlist.txt
docs/usage.rst
docs/docs/sample.png
docs/reference/index.rst
docs/reference/nose_htmloutput.rst
src/nose_html_reporting/__init__.py
src/nose_html_reporting.egg-info/PKG-INFO
src/nose_html_reporting.egg-info/SOURCES.txt
src/nose_html_reporting.egg-info/dependency_links.txt
src/nose_html_reporting.egg-info/entry_points.txt
src/nose_html_reporting.egg-info/not-zip-safe
src/nose_html_reporting.egg-info/requires.txt
src/nose_html_reporting.egg-info/top_level.txt
src/nose_html_reporting/templates/report.html
src/nose_html_reporting/templates/report2.jinja2
tests/nose_report2_test.html
tests/nose_runner.py
tests/nosetests.py
tests/test1_report2.html
tests/test_nose_htmloutput.py
tests/test_sample.py