Metadata-Version: 1.1
Name: nose-html-reporting
Version: 0.2.3
Summary: Nose plugin that generates a nice html test report with ability of using template based on jinja2 templates from any folder.
Home-page: https://github.com/lysenkoivan/nose-html-reporting
Author: Ivan Lysenko
Author-email: lysenko_i@mail.ru
License: BSD
Keywords: nose,plugin,html,template
Platform: UNKNOWN
Classifier: Development Status :: 5 - Production/Stable
Classifier: Intended Audience :: Developers
Classifier: License :: OSI Approved :: BSD License
Classifier: Operating System :: Unix
Classifier: Operating System :: POSIX
Classifier: Operating System :: Microsoft :: Windows
Classifier: Programming Language :: Python
Classifier: Programming Language :: Python :: 2.6
Classifier: Programming Language :: Python :: 2.7
Classifier: Programming Language :: Python :: 3
Classifier: Programming Language :: Python :: 3.3
Classifier: Programming Language :: Python :: 3.4
Classifier: Programming Language :: Python :: Implementation :: CPython
Classifier: Programming Language :: Python :: Implementation :: PyPy
Classifier: Topic :: Utilities
